drope/__init__.py
drope/__main__.py
drope/cmdline.py
drope/server.py
drope/static/index.html
drope/static/script.js
drope/static/style.css
drope-0.4.0.dist-info/LICENSE
drope-0.4.0.dist-info/METADATA
drope-0.4.0.dist-info/WHEEL
drope-0.4.0.dist-info/entry_points.txt
drope-0.4.0.dist-info/top_level.txt
drope-0.4.0.dist-info/RECORD
