Metadata-Version: 2.1
Name: drope
Version: 0.4.0
Summary: A utility for receiving file uploads
Home-page: https://github.com/jvstme/drope
Classifier: Programming Language :: Python :: 3
Classifier: License :: OSI Approved :: MIT License
Classifier: Operating System :: OS Independent
Classifier: Topic :: Utilities
Classifier: Topic :: Communications :: File Sharing
Requires-Python: >=3.6
License-File: LICENSE
Requires-Dist: aiofiles (~=0.8)
Requires-Dist: aiohttp (~=3.8)
Provides-Extra: dev
Requires-Dist: pytest ; extra == 'dev'
Requires-Dist: pytest-aiohttp ; extra == 'dev'
